{"schemaVersion":1,"dataKind":"ranking-year","indicatorId":"PCPIPCH","year":1995,"valuesByCountry":{"ABW":3.413,"AGO":2672.23,"ALB":7.794,"ARE":4.33,"ARM":176.743,"ATG":2.737,"AUS":4.626,"AUT":1.611,"AZE":411.76,"BDI":18.926,"BEL":1.265,"BEN":14.458,"BFA":7.772,"BGD":8.857,"BGR":62.1,"BHR":3.139,"BHS":2.023,"BIH":12.901,"BLR":709.297,"BLZ":2.89,"BOL":10.192,"BRA":66.008,"BRB":2.838,"BRN":5.967,"BTN":7.084,"BWA":10.5,"CAF":19.2,"CAN":2.149,"CHE":1.798,"CHL":8.233,"CHN":16.794,"CIV":14.1,"CMR":25.805,"COD":541.801,"COG":6.3,"COL":20.884,"COM":3.15,"CPV":8.41,"CRI":23.186,"CYP":2.612,"DEU":1.733,"DJI":4.886,"DMA":1.293,"DNK":2.031,"DOM":12.536,"DZA":29.8,"ECU":22.886,"EGY":9.361,"ERI":11.983,"ESP":4.674,"EST":29.003,"ETH":13.354,"FIN":0.398,"FJI":2.183,"FRA":1.77,"G001":16.183,"G110":2.81,"G119":2.286,"G163":2.445,"G200":40.704,"G205":40.142,"G400":26.326,"G505":11.804,"G510":6.989,"G903":138.013,"G998":5.525,"GAB":9.647,"GBR":2.63,"GHA":59.317,"GIN":5.554,"GMB":6.981,"GNB":45.133,"GNQ":19.872,"GRC":8.757,"GRD":3.027,"GTM":8.414,"GUY":12.222,"GX123":3.965,"HKG":9.034,"HND":29.477,"HRV":1.963,"HTI":30.2,"HUN":28.303,"IDN":9.415,"IND":9.96,"IRL":2.518,"IRN":49.32,"ISL":1.655,"ISR":10.043,"ITA":5.419,"JAM":19.91,"JOR":2.353,"JPN":-0.088,"KAZ":176.379,"KEN":1.554,"KGZ":42.174,"KHM":10.077,"KIR":4.1,"KNA":3,"KOR":4.481,"LAO":19.075,"LBN":10.282,"LBY":8.342,"LCA":5.863,"LKA":7.675,"LSO":9.724,"LUX":1.9,"LVA":25,"MAR":6.287,"MDA":30.216,"MDG":49.036,"MDV":5.488,"MEX":35.061,"MKD":16.374,"MLI":11.643,"MLT":3.973,"MNG":0.218,"MOZ":47.668,"MRT":6.544,"MUS":6.026,"MWI":83.148,"MYS":3.468,"NAM":11.123,"NER":10.858,"NIC":11.118,"NLD":1.349,"NOR":2.445,"NPL":7.677,"NZL":3.755,"OMN":-1.131,"PAK":13.029,"PAN":0.939,"PER":11.131,"PHL":6.908,"PNG":17.281,"POL":27.875,"PRI":1.915,"PRT":3.969,"PRY":13.478,"QAT":3.009,"ROU":32.272,"RUS":197.3,"RWA":55.967,"SAU":5.133,"SDN":68.375,"SEN":8.076,"SGP":1.725,"SLB":9.612,"SLE":25.987,"SLV":10.03,"STP":36.8,"SUR":24.162,"SVK":10.95,"SVN":13.572,"SWE":2.464,"SWZ":12.289,"SYC":0.505,"SYR":7.722,"TCD":5.364,"TGO":15.797,"THA":5.796,"TJK":612.481,"TKM":1005.261,"TON":-0.48,"TTO":5.272,"TUN":6.232,"TUR":89.564,"TWN":3.666,"TZA":26.77,"UGA":6.787,"UKR":376.746,"URY":42.248,"USA":2.805,"UZB":304.597,"VCT":2.391,"VEN":59.923,"VNM":16.926,"VUT":2.23,"WSM":-2.926,"ZAF":8.761,"ZMB":31.456}}