{"schemaVersion":1,"dataKind":"ranking-year","indicatorId":"LE","year":2022,"valuesByCountry":{"AND":0.049,"AUS":13.563,"AUT":4.442,"BEL":5.134,"CAN":19.748,"CHE":5.186,"CYP":0.467,"CZE":4.985,"DEU":41.747,"DNK":3.161,"ESP":20.548,"EST":0.681,"FIN":2.618,"FRA":28.589,"G110":113.18,"G119":111.417,"G163":110.793,"GBR":32.957,"GRC":4.141,"GX123":124.429,"HKG":3.635,"HRV":1.598,"IRL":2.595,"ISL":0.211,"ISR":4.187,"ITA":23.1,"JPN":67.225,"KOR":28.089,"LIE":0.043,"LTU":1.421,"LUX":0.501,"LVA":0.886,"MAC":0.365,"MLT":0.284,"NLD":9.546,"NOR":2.849,"NZL":2.842,"PRI":1.117,"PRT":5.163,"SGP":3.79,"SVK":2.427,"SVN":1.083,"SWE":5.199,"TWN":11.418,"USA":158.294}}