{"schemaVersion":1,"dataKind":"ranking-year","indicatorId":"BCA_NGDPD","year":2016,"valuesByCountry":{"ABW":4.557,"AFG":9.029,"AGO":-2.649,"ALB":-7.572,"ARE":3.458,"ARG":-2.713,"ARM":-0.957,"ATG":-2.388,"AUS":-3.455,"AUT":2.574,"AZE":-3.604,"BDI":-11.061,"BEL":0.554,"BEN":-2.997,"BFA":-6.08,"BGD":1.607,"BGR":3.027,"BHR":-4.406,"BHS":-12.395,"BIH":-4.697,"BLR":-3.379,"BLZ":-7.298,"BOL":-4.584,"BRA":-1.699,"BRB":-3.623,"BRN":12.891,"BTN":-29.006,"BWA":7.973,"CAF":-0.46,"CAN":-3.088,"CHE":7.11,"CHL":-2.622,"CHN":1.671,"CIV":-0.856,"CMR":-3.069,"COD":-3.871,"COG":-45.252,"COL":-4.452,"COM":-4.371,"CPV":-3.441,"CRI":-2.137,"CYP":-3.951,"CZE":1.759,"DEU":8.909,"DJI":-1,"DMA":-8.988,"DNK":7.088,"DOM":-1.077,"DZA":-14.645,"ECU":0.913,"EGY":-5.643,"ERI":13.433,"ESP":3.147,"EST":0.978,"ETH":-10.908,"FIN":-1.972,"FJI":-3.538,"FRA":-0.528,"FSM":13.567,"G110":0.831,"G119":-0.11,"G163":3.315,"G200":-0.363,"G205":-2.199,"G400":-3.978,"G505":1.266,"G510":3.951,"G603":-3.081,"G903":-0.273,"G998":3.489,"GAB":-5.414,"GBR":-5.245,"GEO":-12.211,"GHA":-5.06,"GIN":-30.656,"GMB":-9.221,"GNB":1.358,"GNQ":-25.982,"GRC":-2.363,"GRD":-8.849,"GTM":0.965,"GUY":1.453,"GX123":4.825,"HKG":3.958,"HND":-3.144,"HRV":2.116,"HTI":-1.7,"HUN":4.372,"IDN":-1.819,"IND":-0.634,"IRL":-1.244,"IRN":2.772,"IRQ":-6.858,"ISL":8.921,"ISR":3.198,"ITA":2.461,"JAM":-0.291,"JOR":-8.817,"JPN":3.87,"KAZ":-5.073,"KEN":-4.127,"KGZ":-11.625,"KHM":-6.867,"KIR":9.302,"KNA":-12.081,"KOR":6.202,"KOS":-7.937,"KWT":-4.626,"LAO":-8.708,"LBN":-20.692,"LBR":-21.716,"LBY":-9.425,"LCA":-6.338,"LIE":29.673,"LKA":-1.982,"LSO":-10.195,"LTU":-1.008,"LUX":7.401,"LVA":1.78,"MAC":26.602,"MAR":-3.75,"MDA":-3.614,"MDG":0.482,"MDV":-23.474,"MEX":-2.273,"MHL":16.168,"MKD":-2.615,"MLI":-6.057,"MLT":-0.551,"MMR":-5.141,"MNE":-16.308,"MNG":-6.273,"MOZ":-31.866,"MRT":-11.019,"MUS":-3.901,"MWI":-13.105,"MYS":2.393,"NAM":-16.502,"NER":-11.417,"NGA":0.89,"NIC":-8.483,"NLD":7.183,"NOR":5.298,"NPL":5.459,"NRU":4.194,"NZL":-2.076,"OMN":-16.555,"PAK":-1.582,"PAN":-7.543,"PER":-2.214,"PHL":-0.376,"PLW":-16.029,"PNG":13.638,"POL":-1.07,"PRT":1.421,"PRY":4.589,"QAT":-5.45,"ROU":-2.085,"RUS":1.911,"RWA":-15.48,"SAU":-3.913,"SDN":-6.493,"SEN":-4.188,"SGP":18.027,"SLB":-3.726,"SLE":-4.867,"SLV":-2.274,"SOM":-5.521,"SRB":-2.816,"SSD":-7.634,"STP":-6.36,"SUR":-4.838,"SVK":-1.454,"SVN":5.284,"SWE":2.047,"SWZ":8.072,"SYC":-2.867,"SYR":-2.843,"TCD":-4.085,"TGO":-7.192,"THA":10.508,"TJK":-4.158,"TKM":-26.807,"TLS":-33.191,"TON":-7.48,"TTO":-3.286,"TUN":-9.708,"TUR":-2.547,"TUV":29.876,"TWN":13.121,"TZA":-4.221,"UGA":-2.633,"UKR":-1.493,"URY":0.824,"USA":-2.107,"UZB":0.219,"VCT":-13.084,"VEN":-3.427,"VNM":0.248,"VUT":-7.5,"WBG":-13.907,"WSM":-4.233,"YEM":-25.74,"ZAF":-2.676,"ZMB":-3.264,"ZWE":-2.384},"yearsByCountry":{"SYR":2010}}