{"schemaVersion":1,"dataKind":"ranking-year","indicatorId":"GOODS_TRADE_BALANCE","year":1949,"valuesByCountry":{"AFG":-5,"AGO":19.1,"ARG":-136.1,"ASM":0,"ATG":-1.077,"AUS":99.91,"AUT":-306.02,"BEL":-30.7,"BEN":-2.151,"BGR":-33,"BHR":15,"BHS":-15.5,"BLZ":-3,"BOL":10.6,"BRA":-56,"BRB":-8.972,"BRN":10.5,"CAN":171.36,"CHE":-76.378,"CHL":-10.8,"CHN":133,"CMR":-15.5,"COD":7,"COG":-41,"COL":70.6,"CPV":-2.843,"CRI":7.8,"CUB":127,"CYP":-10.345,"DJI":-2,"DNK":-125.506,"DOM":21.299,"DZA":-122.384,"ECU":-13.62,"EGY":-153.469,"ESP":-63,"FIN":68.758,"FJI":-0.475,"FRA":-22.285,"FRO":6.1,"G001":-3627.056,"GBR":-1604.39,"GHA":16.937,"GLP":-0.446,"GMB":0.974,"GNB":-0.512,"GNQ":-20,"GRC":-292.968,"GRL":-3,"GTM":-15.75,"GUF":-3.953,"GUM":-9,"GUY":-2.39,"HKG":-97.817,"HND":4.9,"HTI":3.934,"HUN":101,"IND":-643,"IRL":-259.086,"IRN":259.124,"IRQ":-52.003,"ISL":-14.99,"ISR":-300.9,"ITA":-423.38,"JAM":-26.468,"JOR":-34.872,"JPN":-394.697,"KEN":-142,"KOR":-124.5,"LBY":-14.89,"LCA":-3.327,"LKA":9.793,"MAC":-39,"MAR":-172.402,"MDG":-33,"MDV":-2,"MEX":-11.33,"MLT":-53.135,"MMR":75.393,"MOZ":-31,"MTQ":-10.399,"MUS":4.031,"MWI":-3.393,"MYS":140.225,"NCL":-6,"NER":0.277,"NGA":84.873,"NIC":2.33,"NLD":-589.18,"NOR":-378.554,"NRU":2,"NZL":98.933,"PAK":-68.006,"PER":-12.574,"PHL":-396.5,"PNG":-11.138,"POL":59.921,"PRT":-190.025,"PRY":0.65,"PYF":-2,"QAT":4,"REU":1.913,"ROU":64,"SAU":208,"SEN":-49,"SGP":-175.811,"SLB":0.184,"SLE":4.318,"SLV":14.16,"SPM":0,"STP":0,"SUR":-2.015,"SWE":-24.64,"SYC":1,"SYR":-181.7,"TGO":-5,"THA":81,"TON":-1.7,"TTO":-12.564,"TUN":-42.894,"TUR":-97.9,"TWN":-41.8,"TZA":-26.512,"UGA":42,"URY":11,"USA":4507,"VCT":-0.685,"VEN":62.385,"VUT":1.593,"WSM":2,"ZAF":-112.05,"ZMB":48.3,"ZWE":-91.4},"yearsByCountry":{"BGR":1948,"CHN":1948,"ROU":1948}}